{"image_path": "/home/hyem/workspace/frankmocap_notebooks/images/IODxDxX7oi/scene_00006410.jpg", "body_bbox_list": [[87, 183, 180, 286], [415, 277, 148, 205], [471, 238, 37, 69], [374, 314, 45, 36]], "hand_bbox_list": [{"left_hand": [197.65255737304688, 318.0877380371094, 83.62530517578125, 24.933563232421875], "right_hand": [197.65255737304688, 318.0877380371094, 83.62530517578125, 24.933563232421875]}, {"left_hand": null, "right_hand": null}, {"left_hand": null, "right_hand": null}, {"left_hand": null, "right_hand": null}]}