{"image_path": "/home/hyem/workspace/frankmocap_notebooks/images/D9H-eRIROA/scene_00007433.jpg", "body_bbox_list": [[477, 189, 267, 432], [665, 193, 229, 340], [738, 151, 93, 137], [774, 199, 61, 69]], "hand_bbox_list": [{"left_hand": [496.4470520019531, 333.4222717285156, 24.006561279296875, 27.53948974609375], "right_hand": [470.89227294921875, 335.18212890625, 28.556060791015625, 31.213653564453125]}, {"left_hand": null, "right_hand": null}, {"left_hand": null, "right_hand": null}, {"left_hand": null, "right_hand": null}]}